ckanext/__init__.py
ckanext/or_facet/__init__.py
ckanext/or_facet/plugin.py
ckanext/or_facet/templates/or_facet/facet_switcher.html
ckanext/or_facet/tests/__init__.py
ckanext/or_facet/tests/test_plugin.py
ckanext_or_facet-0.3.1.dist-info/METADATA
ckanext_or_facet-0.3.1.dist-info/WHEEL
ckanext_or_facet-0.3.1.dist-info/entry_points.txt
ckanext_or_facet-0.3.1.dist-info/top_level.txt
ckanext_or_facet-0.3.1.dist-info/RECORD
